duckdb_utils/__init__.py
duckdb_utils/__main__.py
duckdb_utils/cli.py
duckdb_utils/db.py
duckdb_utils-0.1.0a4.dist-info/LICENSE
duckdb_utils-0.1.0a4.dist-info/METADATA
duckdb_utils-0.1.0a4.dist-info/WHEEL
duckdb_utils-0.1.0a4.dist-info/entry_points.txt
duckdb_utils-0.1.0a4.dist-info/top_level.txt
duckdb_utils-0.1.0a4.dist-info/RECORD
