Metadata-Version: 2.1
Name: duckdb-utils
Version: 0.1.0a4
Home-page: https://github.com/Florents-Tselai/duckdb-utils
Author: Florents Tselai
License: BSD License
Project-URL: Issues, https://github.com/Florents-Tselai/duckdb-utils/issues
Project-URL: CI, https://github.com/Florents-Tselai/duckdb-utils/actions
Project-URL: Changelog, https://github.com/Florents-Tselai/duckdb-utils/releases
Requires-Python: >=3.7
License-File: LICENSE
Requires-Dist: setuptools
Requires-Dist: pip
Requires-Dist: sqlite-utils
Requires-Dist: duckdb
Requires-Dist: tabulate
Requires-Dist: click
Requires-Dist: click-default-group >=1.2.3
Provides-Extra: test
Requires-Dist: pytest ; extra == 'test'
Requires-Dist: pytest-cov ; extra == 'test'
Requires-Dist: black ; extra == 'test'
Requires-Dist: ruff ; extra == 'test'
